racerts/__init__.py
racerts/cli.py
racerts/conformer_generator.py
racerts/utils.py
racerts/visualizer.py
racerts/embedder/__init__.py
racerts/embedder/embedder.py
racerts/embedder/utils.py
racerts/mol_getter/__init__.py
racerts/mol_getter/mol_getter.py
racerts/optimizer/__init__.py
racerts/optimizer/ff_optimizer.py
racerts/pruner/__init__.py
racerts/pruner/pruner.py
racerts-0.1.6.dist-info/licenses/LICENSE
racerts-0.1.6.dist-info/METADATA
racerts-0.1.6.dist-info/WHEEL
racerts-0.1.6.dist-info/entry_points.txt
racerts-0.1.6.dist-info/top_level.txt
racerts-0.1.6.dist-info/RECORD
