Metadata-Version: 2.4
Name: racerts
Version: 0.1.6
Summary: Rapid Conformer Ensemble with RDKit for Transition States
Author-email: "Stefan P. Schmid" <stefan.schmid@chem.ethz.ch>, Henrik Seng <heseng@ethz.ch>, Thibault Kläy <thibault.klay@epfl.ch>, Kjell Jorner <kjell.jorner@chem.ethz.ch>
License-Expression: MIT
Project-URL: Homepage, https://github.com/digital-chemistry-laboratory/racerts/
Project-URL: Documentation, https://digital-chemistry-laboratory.github.io/racerts/
Requires-Python: >=3.10
License-File: LICENSE
Requires-Dist: rdkit>=2023.9.6
Requires-Dist: numpy>=1.26.4
Requires-Dist: ipython>=7.34.0
Requires-Dist: py3Dmol>=2.0.0
Provides-Extra: dev
Requires-Dist: black>=21.12b0; extra == "dev"
Requires-Dist: flake8>=6.1.0; extra == "dev"
Requires-Dist: isort>=5.12.0; extra == "dev"
Dynamic: license-file
